{"id": 100909, "title": "August 10, 2017 - Yesterday, a Russian spy plane was spotted over New Jersey. The Russian pilot was overheard saying, \"You know, Siberia’s not so bad.\"", "tags": [{"tid": 7405, "type": {"name": "jokes", "title": "Jokes category", "id": 6}, "name": "News", "description": "", "slug": "jokes/news", "tags": "", "content": 0, "data": null, "status": 1, "hrefTag": "news"}, {"tid": 7154, "type": {"name": "tags", "title": "Tags", "id": 2}, "name": "Russia", "description": "", "slug": "category/tags/russia", "tags": "", "content": 11, "data": [], "status": 1, "hrefTag": "russia"}, {"tid": 441, "type": {"name": "tags", "title": "Tags", "id": 2}, "name": "New Jersey", "description": "", "slug": "category/tags/new-jersey", "tags": "", "content": 2, "data": null, "status": 1, "hrefTag": "new-jersey"}], "body": "Yesterday, a Russian spy plane was spotted over New Jersey. The Russian pilot was overheard saying, \"You know, Siberia’s not so bad.\"", "thumb": "http://cdn.teamcococdn.com/image/650x650,frame:1/img-8307-577dabb052226.jpg", "thumbWithText": "http://cdn.teamcococdn.com/jokes/100909/1,1/650/jokes/august-10-2017-yesterday-a-russian-spy-plane-was-spotted-over-new-jersey-the-russian-pilot-was-overheard-saying-you-know-siberia-s-not-so-bad.jpg", "credit-name": "Conan O'Brien", "credit-date": "August 10, 2017", "slug": "jokes/august-10-2017-yesterday-a-russian-spy-plane-was-spotted-over-new-jersey-the-russian-pilot-was-overheard-saying-you-know-siberia-s-not-so-bad", "hier1": "", "tag": "main"}