{"id": 102567, "title": "January 29, 2018 - In Florida, a 7-year-old boy was arrested for punching his teacher. Or as they call that in Florida, \"a prodigy.\"", "tags": [{"tid": 5947, "type": {"name": "tags", "title": "Tags", "id": 2}, "name": "Florida", "description": "", "slug": "/category/tags/florida", "tags": "", "content": 1, "data": {"name": "Florida", "type": "2", "slug": "/category/tags/florida", "status": "1", "sponsor_category": "", "description": "", "content": "0", "_display": []}, "status": 1, "hrefTag": "florida"}, {"tid": 7405, "type": {"name": "jokes", "title": "Jokes category", "id": 6}, "name": "News", "description": "", "slug": "jokes/news", "tags": "", "content": 0, "data": null, "status": 1, "hrefTag": "news"}, {"tid": 2459, "type": {"name": "tags", "title": "Tags", "id": 2}, "name": "Children", "description": "", "slug": "category/tags/children", "tags": "", "content": 16, "data": null, "status": 1, "hrefTag": "children"}], "body": "In Florida, a 7-year-old boy was arrested for punching his teacher. Or as they call that in Florida, \"a prodigy.\"", "thumb": "http://cdn.teamcococdn.com/image/650x650,frame:1/img-0034-5a6fcff482b02.jpg", "thumbWithText": "http://cdn.teamcococdn.com/jokes/102567/1,1/650/jokes/january-29-2018-in-florida-a-7-year-old-boy-was-arrested-for-punching-his-teacher-or-as-they-call-that-in-florida-a-prodigy.jpg", "credit-name": "Conan O'Brien", "credit-date": "January 29, 2018", "slug": "jokes/january-29-2018-in-florida-a-7-year-old-boy-was-arrested-for-punching-his-teacher-or-as-they-call-that-in-florida-a-prodigy", "hier1": "", "tag": "main"}