{"id": 103432, "title": "April 17, 2018 - It was reported today that President Trump has been pushing for women's health programs that are based on abstinence. Trump said, \"It was actually my wife’s idea…\"", "tags": [{"tid": 7403, "type": {"name": "jokes", "title": "Jokes category", "id": 6}, "name": "Politics", "description": "", "slug": "jokes/politics", "tags": "", "content": 0, "data": null, "status": 1, "hrefTag": "politics"}, {"tid": 1397, "type": {"name": "tags", "title": "Tags", "id": 2}, "name": "Donald Trump", "description": "", "slug": "category/tags/donald-trump", "tags": "", "content": 206, "data": null, "status": 1, "hrefTag": "donald-trump"}, {"tid": 7341, "type": {"name": "tags", "title": "Tags", "id": 2}, "name": "US Presidents", "description": "", "slug": "category/tags/us-presidents", "tags": "", "content": 0, "data": [], "status": 1, "hrefTag": "us-presidents"}, {"tid": 6708, "type": {"name": "tags", "title": "Tags", "id": 2}, "name": "Health", "description": "", "slug": "category/tags/health", "tags": "", "content": 1, "data": [], "status": 1, "hrefTag": "health"}, {"tid": 7384, "type": {"name": "tags", "title": "Tags", "id": 2}, "name": "Women", "description": "", "slug": "category/tags/women", "tags": "", "content": 2, "data": [], "status": 1, "hrefTag": "women"}], "body": "It was reported today that President Trump has been pushing for women's health programs that are based on abstinence. Trump said, \"It was actually my wife’s idea…\"", "thumb": "http://cdn.teamcococdn.com/image/650x650,frame:1/5d329408dvlpd-5ad693cd59060.jpg", "thumbWithText": "http://cdn.teamcococdn.com/jokes/103432/1,1/650/jokes/april-17-2018-it-was-reported-today-that-president-trump-has-been-pushing-for-women-s-health-programs-that-are-based-on-abstinence-trump-said-it-was-actually-my-wife-s-idea.jpg", "credit-name": "Conan O'Brien", "credit-date": "April 17, 2018", "slug": "jokes/april-17-2018-it-was-reported-today-that-president-trump-has-been-pushing-for-women-s-health-programs-that-are-based-on-abstinence-trump-said-it-was-actually-my-wife-s-idea", "hier1": "", "tag": "main"}