{"id": 103499, "title": "April 17, 2018 - No one on Earth has ever said, \"Hooray! Salmon burgers!\"", "tags": [{"tid": 6643, "type": {"name": "tags", "title": "Tags", "id": 2}, "name": "Food", "description": "", "slug": "category/tags/food", "tags": "", "content": 8, "data": [], "status": 1, "hrefTag": "food"}, {"tid": 7406, "type": {"name": "jokes", "title": "Jokes category", "id": 6}, "name": "Celebs", "description": "", "slug": "jokes/celebs", "tags": "", "content": 0, "data": null, "status": 1, "hrefTag": "celebs"}], "body": "No one on Earth has ever said, \"Hooray! Salmon burgers!\"", "thumb": "http://cdn.teamcococdn.com/image/650x650,frame:1/5d321535dvlpd-5ade1a5e753ae.jpg", "thumbWithText": "http://cdn.teamcococdn.com/jokes/103499/1,1/650/jokes/april-17-2018-no-one-on-earth-has-ever-said-hooray-salmon-burgers.jpg", "credit-name": "@ConanOBrien", "credit-date": "April 17, 2018", "slug": "jokes/april-17-2018-no-one-on-earth-has-ever-said-hooray-salmon-burgers", "hier1": "", "tag": "main"}