{"id": 103974, "title": "June 5, 2018 - The head of Starbucks, Howard Schultz, has announced that he’s leaving the company. Schultz said, \"I can’t keep living a lie… the coffee at Dunkin' Donuts is way better.\"", "tags": [{"tid": 7405, "type": {"name": "jokes", "title": "Jokes category", "id": 6}, "name": "News", "description": "", "slug": "jokes/news", "tags": "", "content": 0, "data": null, "status": 1, "hrefTag": "news"}, {"tid": 975, "type": {"name": "tags", "title": "Tags", "id": 2}, "name": "Starbucks", "description": "", "slug": "category/tags/starbucks", "tags": "", "content": 11, "data": null, "status": 1, "hrefTag": "starbucks"}, {"tid": 6585, "type": {"name": "tags", "title": "Tags", "id": 2}, "name": "Dunkin' Donuts", "description": "", "slug": "category/tags/dunkin-donuts", "tags": "", "content": 1, "data": [], "status": 1, "hrefTag": "dunkin'-donuts"}, {"tid": 6518, "type": {"name": "tags", "title": "Tags", "id": 2}, "name": "Coffee", "description": "", "slug": "category/tags/coffee", "tags": "", "content": 0, "data": [], "status": 1, "hrefTag": "coffee"}], "body": "The head of Starbucks, Howard Schultz, has announced that he’s leaving the company. Schultz said, \"I can’t keep living a lie… the coffee at Dunkin' Donuts is way better.\"", "thumb": "http://cdn.teamcococdn.com/image/650x650,frame:1/img-0040-5a612288e583b.jpg", "thumbWithText": "http://cdn.teamcococdn.com/jokes/103974/1,1/650/jokes/june-5-2018-the-head-of-starbucks-howard-schultz-has-announced-that-he-s-leaving-the-company-schultz-said-i-can-t-keep-living-a-lie-the-coffee-at-dunkin-donuts-is-way-better.jpg", "credit-name": "Conan O'Brien", "credit-date": "June 05, 2018", "slug": "jokes/june-5-2018-the-head-of-starbucks-howard-schultz-has-announced-that-he-s-leaving-the-company-schultz-said-i-can-t-keep-living-a-lie-the-coffee-at-dunkin-donuts-is-way-better", "hier1": "", "tag": "main"}