{"tags": [{"tags": "", "hrefTag": "tech", "status": 1, "slug": "jokes/tech", "tid": 7404, "data": null, "type": {"name": "jokes", "id": 6, "title": "Jokes category"}, "name": "Tech", "description": "", "content": 0}, {"tags": "", "hrefTag": "facebook", "status": 1, "slug": "category/tags/facebook", "tid": 149, "data": null, "type": {"name": "tags", "id": 2, "title": "Tags"}, "name": "Facebook", "description": "", "content": 44}, {"tags": "", "hrefTag": "japan", "status": 1, "slug": "category/tags/japan", "tid": 6781, "data": [], "type": {"name": "tags", "id": 2, "title": "Tags"}, "name": "Japan", "description": "", "content": 4}, {"tags": "", "hrefTag": "social-media", "status": 1, "slug": "category/tags/social-media", "tid": 7198, "data": [], "type": {"name": "tags", "id": 2, "title": "Tags"}, "name": "Social Media", "description": "", "content": 2}], "id": 64355, "thumbWithText": "http://cdn.teamcococdn.com/jokes/64355/1,1/650/jokes/jan-13-2011-according-to-a-new-report-facebook-is-not-popular-in-japan.jpg", "slug": "jokes/jan-13-2011-according-to-a-new-report-facebook-is-not-popular-in-japan", "body": "According to a new report, Facebook is not popular in Japan because Japanese people are traditionally introverted and private. The report was written by someone who has never set foot in a karaoke bar.", "title": "Jan 13, 2011 - According to a new report, Facebook is not popular in Japan", "credit-date": "January 13, 2011", "hier1": "", "thumb": "http://cdn.teamcococdn.com/image/650x650,frame:1/monologue-s1-ef34c313dd24bf5c77bd3eaa04e0510c.jpg", "tag": "main", "credit-name": "Conan O'Brien"}