{"tags": [{"tags": "", "hrefTag": "tech", "status": 1, "slug": "jokes/tech", "tid": 7404, "data": null, "type": {"name": "jokes", "id": 6, "title": "Jokes category"}, "name": "Tech", "description": "", "content": 0}, {"tags": "", "hrefTag": "facebook", "status": 1, "slug": "category/tags/facebook", "tid": 149, "data": null, "type": {"name": "tags", "id": 2, "title": "Tags"}, "name": "Facebook", "description": "", "content": 44}, {"tags": "", "hrefTag": "prison", "status": 1, "slug": "category/tags/prison", "tid": 7093, "data": [], "type": {"name": "tags", "id": 2, "title": "Tags"}, "name": "Prison", "description": "", "content": 3}, {"tags": "", "hrefTag": "social-media", "status": 1, "slug": "category/tags/social-media", "tid": 7198, "data": [], "type": {"name": "tags", "id": 2, "title": "Tags"}, "name": "Social Media", "description": "", "content": 2}], "id": 64509, "thumbWithText": "http://cdn.teamcococdn.com/jokes/64509/1,1/650/jokes/feb-10-2011-a-south-carolina-legislator-wants-to-ban-prison-inmates.jpg", "slug": "jokes/feb-10-2011-a-south-carolina-legislator-wants-to-ban-prison-inmates", "body": "A South Carolina legislator wants to ban prison inmates from using Facebook.  A spokesperson for the inmates said, \"They can take away our Facebook but they can't stop us from poking each other.\"", "title": "Feb 10, 2011 - A South Carolina legislator wants to ban prison inmates", "credit-date": "February 10, 2011", "hier1": "", "thumb": "http://cdn.teamcococdn.com/image/650x650,frame:1/monologue-s1-b12813d005f1b6924ab29e7feaa1fe25.jpg", "tag": "main", "credit-name": "Conan O'Brien"}