{"tags": [{"tags": "", "hrefTag": "news", "status": 1, "slug": "jokes/news", "tid": 7405, "data": null, "type": {"name": "jokes", "id": 6, "title": "Jokes category"}, "name": "News", "description": "", "content": 0}, {"tags": "", "hrefTag": "chilean-miners", "status": 1, "slug": "category/tags/chilean-miners", "tid": 6494, "data": [], "type": {"name": "tags", "id": 2, "title": "Tags"}, "name": "Chilean Miners", "description": "", "content": 0}, {"tags": "", "hrefTag": "work", "status": 1, "slug": "category/tags/work", "tid": 7386, "data": [], "type": {"name": "tags", "id": 2, "title": "Tags"}, "name": "Work", "description": "", "content": 0}], "id": 65206, "thumbWithText": "http://cdn.teamcococdn.com/jokes/65206/1,1/650/jokes/aug-8-2011-a-year-after-they-were-rescued-most-of-the-chilean-miners.jpg", "slug": "jokes/aug-8-2011-a-year-after-they-were-rescued-most-of-the-chilean-miners", "body": "A year after they were rescued, most of the Chilean miners are still unemployed.  Unfortunately, most employers are hesitant to hire them because of the giant gap in their resume.", "title": "Aug 8, 2011 - A year after they were rescued, most of the Chilean miners", "credit-date": "August 08, 2011", "hier1": "", "thumb": "http://cdn.teamcococdn.com/image/650x650,frame:1/monologue-s1-d0071fd02a612c2062116060d73ec02e.jpg", "tag": "main", "credit-name": "Conan O'Brien"}