{"tags": [{"tags": "", "hrefTag": "news", "status": 1, "slug": "jokes/news", "tid": 7405, "data": null, "type": {"name": "jokes", "id": 6, "title": "Jokes category"}, "name": "News", "description": "", "content": 0}, {"tags": "", "hrefTag": "animals", "status": 1, "slug": "category/tags/animals", "tid": 6348, "data": [], "type": {"name": "tags", "id": 2, "title": "Tags"}, "name": "Animals", "description": "", "content": 16}, {"tags": "", "hrefTag": "tortoises", "status": 1, "slug": "category/tags/tortoises", "tid": 7312, "data": [], "type": {"name": "tags", "id": 2, "title": "Tags"}, "name": "Tortoises", "description": "", "content": 0}], "id": 65764, "thumbWithText": "http://cdn.teamcococdn.com/jokes/65764/1,1/650/jokes/jan-11-2012-a-tortoise-thought-to-have-gone-extinct-150-years-ago-has.jpg", "slug": "jokes/jan-11-2012-a-tortoise-thought-to-have-gone-extinct-150-years-ago-has", "body": "A tortoise thought to have gone extinct 150 years ago has reappeared.  Even more surprising, his first words upon reappearing were, \"Where's my money, bitch?\"", "title": "Jan 11, 2012 - A tortoise thought to have gone extinct 150 years ago has", "credit-date": "January 11, 2012", "hier1": "", "thumb": "http://cdn.teamcococdn.com/image/650x650,frame:1/monologue-s2-ab2fa29db63a2b0cf4447b24fd0331f6.jpg", "tag": "main", "credit-name": "Conan O'Brien"}