{"tags": [{"tags": "", "hrefTag": "news", "status": 1, "slug": "jokes/news", "tid": 7405, "data": null, "type": {"name": "jokes", "id": 6, "title": "Jokes category"}, "name": "News", "description": "", "content": 0}, {"tags": "", "hrefTag": "pizza-hut", "status": 1, "slug": "/category/tags/pizza-hut", "tid": 5688, "data": {"_display": [], "slug": "/category/tags/pizza-hut", "content": "0", "type": "2", "name": "Pizza Hut", "status": "1", "sponsor_category": "", "description": ""}, "type": {"name": "tags", "id": 2, "title": "Tags"}, "name": "Pizza Hut", "description": "", "content": 5}, {"tags": "", "hrefTag": "restaurants", "status": 1, "slug": "category/tags/restaurants", "tid": 7133, "data": [], "type": {"name": "tags", "id": 2, "title": "Tags"}, "name": "Restaurants", "description": "", "content": 2}, {"tags": "", "hrefTag": "college", "status": 1, "slug": "/category/tags/college", "tid": 5345, "data": {"_display": [], "slug": "/category/tags/college", "content": "0", "type": "2", "name": "College", "status": "1", "sponsor_category": "", "description": ""}, "type": {"name": "tags", "id": 2, "title": "Tags"}, "name": "College", "description": "", "content": 4}, {"tags": "", "hrefTag": "dating", "status": 1, "slug": "category/tags/dating", "tid": 6547, "data": [], "type": {"name": "tags", "id": 2, "title": "Tags"}, "name": "Dating", "description": "", "content": 5}], "id": 65963, "thumbWithText": "http://cdn.teamcococdn.com/jokes/65963/1,1/650/jokes/feb-28-2012-the-ceo-of-pizza-hut-said-that-when-he-was-in-college-he-used.jpg", "slug": "jokes/feb-28-2012-the-ceo-of-pizza-hut-said-that-when-he-was-in-college-he-used", "body": "The CEO of Pizza Hut said that when he was in college, he used to bring his dates to Pizza Hut.  When asked where he brought them on the second date he said, \"There were no second dates.\"", "title": "Feb 28, 2012 - The CEO of Pizza Hut said that when he was in college, he used", "credit-date": "February 28, 2012", "hier1": "", "thumb": "http://cdn.teamcococdn.com/image/650x650,frame:1/monologue-s2-712b558fe6f65359147e4fbf01ae4862.jpg", "tag": "main", "credit-name": "Conan O'Brien"}