{"tags": [{"tags": "", "hrefTag": "politics", "status": 1, "slug": "jokes/politics", "tid": 7403, "data": null, "type": {"name": "jokes", "id": 6, "title": "Jokes category"}, "name": "Politics", "description": "", "content": 0}, {"tags": "", "hrefTag": "barack-obama", "status": 1, "slug": "category/tags/barack-obama", "tid": 397, "data": null, "type": {"name": "tags", "id": 2, "title": "Tags"}, "name": "Barack Obama", "description": "", "content": 126}, {"tags": "", "hrefTag": "bill-clinton", "status": 1, "slug": "/category/tags/bill-clinton", "tid": 5287, "data": {"_display": [], "slug": "/category/tags/bill-clinton", "content": "0", "type": "2", "name": "Bill Clinton", "status": "1", "sponsor_category": "", "description": ""}, "type": {"name": "tags", "id": 2, "title": "Tags"}, "name": "Bill Clinton", "description": "", "content": 19}, {"tags": "", "hrefTag": "us-presidents", "status": 1, "slug": "category/tags/us-presidents", "tid": 7341, "data": [], "type": {"name": "tags", "id": 2, "title": "Tags"}, "name": "US Presidents", "description": "", "content": 0}], "id": 66595, "thumbWithText": "http://cdn.teamcococdn.com/jokes/66595/1,1/650/jokes/sep-6-2012-after-his-speech-president-obama-surprised-clinton-by.jpg", "slug": "jokes/sep-6-2012-after-his-speech-president-obama-surprised-clinton-by", "body": "After his speech, President Obama surprised Clinton by walking on stage and giving him a hug.  Out of habit, when Bill Clinton saw a woman's husband coming at him he threw his shoe and hit in a closet.", "title": "Sep 6, 2012 - After his speech, President Obama surprised Clinton by", "credit-date": "September 06, 2012", "hier1": "", "thumb": "http://cdn.teamcococdn.com/image/650x650,frame:1/monologue-s2-8c0817f71709d25fa3c5b8df19c8d76e.jpg", "tag": "main", "credit-name": "Conan O'Brien"}