{"tags": [{"tags": "", "hrefTag": "celebs", "status": 1, "slug": "jokes/celebs", "tid": 7406, "data": null, "type": {"name": "jokes", "id": 6, "title": "Jokes category"}, "name": "Celebs", "description": "", "content": 0}, {"tags": "", "hrefTag": "dennis-rodman", "status": 1, "slug": "/category/tags/dennis-rodman", "tid": 6051, "data": {"_display": [], "slug": "/category/tags/dennis-rodman", "content": "0", "type": "2", "name": "Dennis Rodman", "status": "1", "sponsor_category": "", "description": ""}, "type": {"name": "tags", "id": 2, "title": "Tags"}, "name": "Dennis Rodman", "description": "", "content": 1}, {"tags": "", "hrefTag": "fbi", "status": 1, "slug": "category/tags/fbi", "tid": 6630, "data": [], "type": {"name": "tags", "id": 2, "title": "Tags"}, "name": "FBI", "description": "", "content": 1}], "id": 67439, "thumbWithText": "http://cdn.teamcococdn.com/jokes/67439/1,1/650/jokes/apr-16-2013-dennis-rodman-claims-the-fbi-wants-to-hire-him-as-an.jpg", "slug": "jokes/apr-16-2013-dennis-rodman-claims-the-fbi-wants-to-hire-him-as-an", "body": "Dennis Rodman claims the FBI wants to hire him as an informant.  Which makes sense because the first thing you want to do as an FBI informant is tell everyone you're an FBI informant.", "title": "Apr 16, 2013 - Dennis Rodman claims the FBI wants to hire him as an", "credit-date": "April 16, 2013", "hier1": "", "thumb": "http://cdn.teamcococdn.com/image/650x650,frame:1/0417_mono2-519c0f21bb982.jpeg", "tag": "main", "credit-name": "Conan O'Brien"}