{"tags": [{"tags": "", "hrefTag": "news", "status": 1, "slug": "jokes/news", "tid": 7405, "data": null, "type": {"name": "jokes", "id": 6, "title": "Jokes category"}, "name": "News", "description": "", "content": 0}, {"tags": "", "hrefTag": "airplanes", "status": 1, "slug": "category/tags/airplanes", "tid": 6330, "data": [], "type": {"name": "tags", "id": 2, "title": "Tags"}, "name": "Airplanes", "description": "", "content": 7}, {"tags": "", "hrefTag": "spirit-airlines", "status": 1, "slug": "category/tags/spirit-airlines", "tid": 7212, "data": [], "type": {"name": "tags", "id": 2, "title": "Tags"}, "name": "Spirit Airlines", "description": "", "content": 0}, {"tags": "", "hrefTag": "alcohol", "status": 1, "slug": "category/tags/alcohol", "tid": 6337, "data": [], "type": {"name": "tags", "id": 2, "title": "Tags"}, "name": "Alcohol", "description": "", "content": 13}, {"tags": "", "hrefTag": "wine", "status": 1, "slug": "category/tags/wine", "tid": 7379, "data": [], "type": {"name": "tags", "id": 2, "title": "Tags"}, "name": "Wine", "description": "", "content": 1}], "id": 67655, "thumbWithText": "http://cdn.teamcococdn.com/jokes/67655/1,1/650/jokes/jun-13-2013-the-budget-airline-spirit-airlines-is-now-serving-canned.jpg", "slug": "jokes/jun-13-2013-the-budget-airline-spirit-airlines-is-now-serving-canned", "body": "The budget airline Spirit Airlines is now serving canned wine. A spokesman for Spirit said, “Hey, if it’s good enough for our pilots, it’s good for our passengers.”", "title": "Jun 13, 2013 - The budget airline Spirit Airlines is now serving canned", "credit-date": "June 13, 2013", "hier1": "", "thumb": "http://cdn.teamcococdn.com/image/650x650,frame:1/monologue-s3-972045633dfd7d578298b617201c19e6.jpg", "tag": "main", "credit-name": "Conan O'Brien"}