{"tags": [{"tags": "", "hrefTag": "sports", "status": 1, "slug": "jokes/sports", "tid": 7407, "data": null, "type": {"name": "jokes", "id": 6, "title": "Jokes category"}, "name": "Sports", "description": "", "content": 0}, {"tags": "", "hrefTag": "detroit", "status": 1, "slug": "category/tags/detroit", "tid": 6562, "data": [], "type": {"name": "tags", "id": 2, "title": "Tags"}, "name": "Detroit", "description": "", "content": 0}, {"tags": "", "hrefTag": "lions", "status": 1, "slug": "category/tags/lions", "tid": 6877, "data": [], "type": {"name": "tags", "id": 2, "title": "Tags"}, "name": "Lions", "description": "", "content": 0}, {"tags": "", "hrefTag": "football", "status": 1, "slug": "category/tags/football", "tid": 2687, "data": null, "type": {"name": "tags", "id": 2, "title": "Tags"}, "name": "Football", "description": "", "content": 19}, {"tags": "", "hrefTag": "money", "status": 1, "slug": "category/tags/money", "tid": 6966, "data": [], "type": {"name": "tags", "id": 2, "title": "Tags"}, "name": "Money", "description": "", "content": 1}], "id": 67726, "thumbWithText": "http://cdn.teamcococdn.com/jokes/67726/1,1/650/jokes/jul-11-2013-the-detroit-lions-quarterback-matthew-stafford-signed-a.jpg", "slug": "jokes/jul-11-2013-the-detroit-lions-quarterback-matthew-stafford-signed-a", "body": "The Detroit Lions Quarterback Matthew Stafford signed a new contract worth $76 million.  They’re paying him $10 million to play quarterback and $66 million to live in Detroit.", "title": "Jul 11, 2013 - The Detroit Lions Quarterback Matthew Stafford signed a", "credit-date": "July 11, 2013", "hier1": "", "thumb": "http://cdn.teamcococdn.com/image/650x650,frame:1/monologue-s3-b04467bd4038436e206e5091ac7dfcb8.jpg", "tag": "main", "credit-name": "Conan O'Brien"}