{"tags": [{"tags": "", "hrefTag": "news", "status": 1, "slug": "jokes/news", "tid": 7405, "data": null, "type": {"name": "jokes", "id": 6, "title": "Jokes category"}, "name": "News", "description": "", "content": 0}, {"tags": "", "hrefTag": "conan", "status": 1, "slug": "category/tags/conan", "tid": 24, "data": null, "type": {"name": "tags", "id": 2, "title": "Tags"}, "name": "CONAN", "description": "", "content": 8}, {"tags": "", "hrefTag": "sons-of-anarchy", "status": 1, "slug": "/category/tags/sons-of-anarchy", "tid": 5515, "data": {"_display": [], "slug": "/category/tags/sons-of-anarchy", "content": "0", "type": "2", "name": "Sons of Anarchy", "status": "1", "sponsor_category": "", "description": ""}, "type": {"name": "tags", "id": 2, "title": "Tags"}, "name": "Sons of Anarchy", "description": "", "content": 45}, {"tags": "", "hrefTag": "fan-fiction", "status": 1, "slug": "category/tags/fan-fiction", "tid": 7525, "data": [], "type": {"name": "tags", "id": 2, "title": "Tags"}, "name": "Fan Fiction", "description": "", "content": 0}], "id": 67883, "thumbWithText": "http://cdn.teamcococdn.com/jokes/67883/1,1/650/jokes/nov-26-2012-is-it-weird-that-all-my-sons-of-anarchy-fan-fiction.jpg", "slug": "jokes/nov-26-2012-is-it-weird-that-all-my-sons-of-anarchy-fan-fiction", "body": "Is it weird that all my “Sons of Anarchy” fan fiction ends with everyone getting along really well?", "title": "Nov 26, 2012 - Is it weird that all my “Sons of Anarchy” fan fiction", "credit-date": "November 26, 2012", "hier1": "", "thumb": "http://cdn.teamcococdn.com/image/650x650,frame:1/monologue-s3-55204a23e5ae2bcea3d4896a05589b60.jpg", "tag": "main", "credit-name": "@ConanOBrien"}