{"tags": [{"tags": "", "hrefTag": "news", "status": 1, "slug": "jokes/news", "tid": 7405, "data": null, "type": {"name": "jokes", "id": 6, "title": "Jokes category"}, "name": "News", "description": "", "content": 0}, {"tags": "", "hrefTag": "conan", "status": 1, "slug": "category/tags/conan", "tid": 24, "data": null, "type": {"name": "tags", "id": 2, "title": "Tags"}, "name": "CONAN", "description": "", "content": 8}, {"tags": "", "hrefTag": "sex", "status": 1, "slug": "category/tags/sex", "tid": 119, "data": null, "type": {"name": "tags", "id": 2, "title": "Tags"}, "name": "Sex", "description": "", "content": 55}], "id": 68040, "thumbWithText": "http://cdn.teamcococdn.com/jokes/68040/1,1/650/jokes/feb-4-2012-turns-out-bingo-bango-bongo-is-not-a-good-thing-to.jpg", "slug": "jokes/feb-4-2012-turns-out-bingo-bango-bongo-is-not-a-good-thing-to", "body": "Turns out “Bingo Bango Bongo!” is not a good thing to yell out during sex.", "title": "Feb 4, 2012 - Turns out “Bingo Bango Bongo!” is not a good thing to", "credit-date": "February 04, 2012", "hier1": "", "thumb": "http://cdn.teamcococdn.com/image/650x650,frame:1/monologue-s2-6f3dffcaa69b32eb857b7bb3dbf8b0fb.jpg", "tag": "main", "credit-name": "@ConanOBrien"}