{"tags": [{"tags": "", "hrefTag": "celebs", "status": 1, "slug": "jokes/celebs", "tid": 7406, "data": null, "type": {"name": "jokes", "id": 6, "title": "Jokes category"}, "name": "Celebs", "description": "", "content": 0}, {"tags": "", "hrefTag": "ceelo-green", "status": 1, "slug": "/category/tags/ceelo-green", "tid": 7783, "data": {"_display": [], "slug": "/category/tags/ceelo-green", "content": "", "type": "2", "name": "CeeLo Green", "status": "1", "sponsor_category": "", "description": ""}, "type": {"name": "tags", "id": 2, "title": "Tags"}, "name": "CeeLo Green", "description": "", "content": 6}, {"tags": "", "hrefTag": "the-voice", "status": 1, "slug": "category/tags/voice", "tid": 1987, "data": null, "type": {"name": "tags", "id": 2, "title": "Tags"}, "name": "The Voice", "description": "", "content": 19}], "id": 78289, "thumbWithText": "http://cdn.teamcococdn.com/jokes/78289/1,1/650/jokes/feb-19-2014-ceelo-green-said-he-won-t-be-back-as-a-judge-on-the-voice-ceelo-said-he-wants-to-spend-more-time-with-his-fami.jpg", "slug": "jokes/feb-19-2014-ceelo-green-said-he-won-t-be-back-as-a-judge-on-the-voice-ceelo-said-he-wants-to-spend-more-time-with-his-fami", "body": "CeeLo Green said he won’t be back as a judge on \"The Voice.\" CeeLo said he wants to spend more time with his family, facing the wrong direction.\r\n", "title": "Feb 19, 2014 - CeeLo Green said he won&rsquo;t be back as a judge on &ldquo;The Voice.&rdquo; CeeLo said he wants to spend more time with his fami", "credit-date": "February 19, 2014", "hier1": "", "thumb": "http://cdn.teamcococdn.com/image/650x650,frame:1/img_3038-53065dc596c45.jpg", "tag": "main", "credit-name": "Conan O'Brien"}