{"tags": [{"tags": "", "hrefTag": "news", "status": 1, "slug": "jokes/news", "tid": 7405, "data": null, "type": {"name": "jokes", "id": 6, "title": "Jokes category"}, "name": "News", "description": "", "content": 0}, {"tags": "", "hrefTag": "vladimir-putin", "status": 1, "slug": "/category/tags/vladimir-putin", "tid": 5051, "data": {"_display": [], "slug": "/category/tags/vladimir-putin", "content": "0", "type": "2", "name": "Vladimir Putin", "description": "", "sponsor_category": ""}, "type": {"name": "tags", "id": 2, "title": "Tags"}, "name": "Vladimir Putin", "description": "", "content": 4}, {"tags": "", "hrefTag": "march-madness", "status": 1, "slug": "/category/tags/march-madness", "tid": 5924, "data": {"_display": [], "slug": "/category/tags/march-madness", "content": "0", "type": "2", "name": "March Madness", "status": "1", "sponsor_category": "", "description": ""}, "type": {"name": "tags", "id": 2, "title": "Tags"}, "name": "March Madness", "description": "", "content": 1}, {"tags": "", "hrefTag": "russia", "status": 1, "slug": "category/tags/russia", "tid": 7154, "data": [], "type": {"name": "tags", "id": 2, "title": "Tags"}, "name": "Russia", "description": "", "content": 5}, {"tags": "", "hrefTag": "basketball", "status": 1, "slug": "category/tags/basketball", "tid": 1281, "data": null, "type": {"name": "tags", "id": 2, "title": "Tags"}, "name": "Basketball", "description": "", "content": 25}], "id": 79699, "thumbWithText": "http://cdn.teamcococdn.com/jokes/79699/1,1/650/jokes/march-15-2014-do-you-think-putin-just-misunderstood-the-term-march-madness.jpg", "slug": "jokes/march-15-2014-do-you-think-putin-just-misunderstood-the-term-march-madness", "body": "Do you think Putin just misunderstood the term \"March Madness\"?", "title": "March 15, 2014 - Do you think Putin just misunderstood the term &ldquo;March Madness&rdquo;?", "credit-date": "March 15, 2014", "hier1": "", "thumb": "http://cdn.teamcococdn.com/image/650x650,frame:1/img_6325-5330572903aaf.jpg", "tag": "main", "credit-name": "@ConanOBrien"}