{"tags": [{"tags": "", "hrefTag": "sports", "status": 1, "slug": "jokes/sports", "tid": 7407, "data": null, "type": {"name": "jokes", "id": 6, "title": "Jokes category"}, "name": "Sports", "description": "", "content": 0}, {"tags": "", "hrefTag": "nfl", "status": 1, "slug": "category/tags/nfl", "tid": 1737, "data": null, "type": {"name": "tags", "id": 2, "title": "Tags"}, "name": "NFL", "description": "", "content": 21}, {"tags": "", "hrefTag": "football", "status": 1, "slug": "category/tags/football", "tid": 2687, "data": null, "type": {"name": "tags", "id": 2, "title": "Tags"}, "name": "Football", "description": "", "content": 19}, {"tags": "", "hrefTag": "death", "status": 1, "slug": "category/tags/death", "tid": 6552, "data": [], "type": {"name": "tags", "id": 2, "title": "Tags"}, "name": "Death", "description": "", "content": 7}, {"tags": "", "hrefTag": "crime", "status": 1, "slug": "category/tags/crime", "tid": 6535, "data": [], "type": {"name": "tags", "id": 2, "title": "Tags"}, "name": "Crime", "description": "", "content": 2}, {"tags": "", "hrefTag": "language", "status": 1, "slug": "category/tags/language", "tid": 6853, "data": [], "type": {"name": "tags", "id": 2, "title": "Tags"}, "name": "Language", "description": "", "content": 1}], "id": 79984, "thumbWithText": "http://cdn.teamcococdn.com/jokes/79984/1,1/650/jokes/march-26-2014-yesterday-the-nfl-announced-some-tough-new-rule-changes-for-next-season-there-will-be-a-10-yard-penalty-for.jpg", "slug": "jokes/march-26-2014-yesterday-the-nfl-announced-some-tough-new-rule-changes-for-next-season-there-will-be-a-10-yard-penalty-for", "body": "The NFL announced some tough new rule changes for next season. There will be a 10-yard penalty for abusive language and a 15-yard penalty for murdering someone.", "title": "March 26, 2014 - Yesterday, the NFL announced some tough new rule changes for next season.  There will be a 10-yard penalty for", "credit-date": "March 26, 2014", "hier1": "", "thumb": "http://cdn.teamcococdn.com/image/650x650,frame:1/206490550212-5334529988a07.jpg", "tag": "main", "credit-name": "Conan O'Brien"}