{"tags": [{"tags": "", "hrefTag": "celebs", "status": 1, "slug": "jokes/celebs", "tid": 7406, "data": null, "type": {"name": "jokes", "id": 6, "title": "Jokes category"}, "name": "Celebs", "description": "", "content": 0}, {"tags": "", "hrefTag": "dr.-dre", "status": 1, "slug": "category/tags/dr-dre", "tid": 6579, "data": [], "type": {"name": "tags", "id": 2, "title": "Tags"}, "name": "Dr. Dre", "description": "", "content": 1}, {"tags": "", "hrefTag": "money", "status": 1, "slug": "category/tags/money", "tid": 6966, "data": [], "type": {"name": "tags", "id": 2, "title": "Tags"}, "name": "Money", "description": "", "content": 1}, {"tags": "", "hrefTag": "hip-hop", "status": 1, "slug": "category/tags/hip-hop", "tid": 6722, "data": [], "type": {"name": "tags", "id": 2, "title": "Tags"}, "name": "Hip-Hop", "description": "", "content": 0}, {"tags": "", "hrefTag": "conan", "status": 1, "slug": "category/tags/conan", "tid": 24, "data": null, "type": {"name": "tags", "id": 2, "title": "Tags"}, "name": "CONAN", "description": "", "content": 8}, {"tags": "", "hrefTag": "work", "status": 1, "slug": "category/tags/work", "tid": 7386, "data": [], "type": {"name": "tags", "id": 2, "title": "Tags"}, "name": "Work", "description": "", "content": 0}], "id": 82147, "thumbWithText": "http://cdn.teamcococdn.com/jokes/82147/1,1/650/jokes/may-12-2014-dr-dre-may-become-the-world-s-first-hip-hop-billionaire-so-maybe-my-mom-was-right-i-should-ve-become-a-doctor.jpg", "slug": "jokes/may-12-2014-dr-dre-may-become-the-world-s-first-hip-hop-billionaire-so-maybe-my-mom-was-right-i-should-ve-become-a-doctor", "body": "Dr. Dre may become the world’s first hip-hop billionaire.  So maybe my mom was right—I should’ve become a doctor.\r\n", "title": "May 12, 2014 - Dr. Dre may become the world&rsquo;s first hip hop billionaire.  So maybe my mom was right&mdash;I should&rsquo;ve become a doctor.", "credit-date": "May 12, 2014", "hier1": "", "thumb": "http://cdn.teamcococdn.com/image/650x650,frame:1/20649_0569_211-53723533eeadd.jpg", "tag": "main", "credit-name": "Conan O'Brien"}