{"tags": [{"tags": "", "hrefTag": "tech", "status": 1, "slug": "jokes/tech", "tid": 7404, "data": null, "type": {"name": "jokes", "id": 6, "title": "Jokes category"}, "name": "Tech", "description": "", "content": 0}, {"tags": "", "hrefTag": "japan", "status": 1, "slug": "category/tags/japan", "tid": 6781, "data": [], "type": {"name": "tags", "id": 2, "title": "Tags"}, "name": "Japan", "description": "", "content": 4}, {"tags": "", "hrefTag": "gadgets", "status": 1, "slug": "category/tags/gadgets", "tid": 6657, "data": [], "type": {"name": "tags", "id": 2, "title": "Tags"}, "name": "Gadgets", "description": "", "content": 0}, {"tags": "", "hrefTag": "conan", "status": 1, "slug": "category/tags/conan", "tid": 24, "data": null, "type": {"name": "tags", "id": 2, "title": "Tags"}, "name": "CONAN", "description": "", "content": 8}, {"tags": "", "hrefTag": "work", "status": 1, "slug": "category/tags/work", "tid": 7386, "data": [], "type": {"name": "tags", "id": 2, "title": "Tags"}, "name": "Work", "description": "", "content": 0}, {"tags": "", "hrefTag": "quiznos", "status": 1, "slug": "/category/tags/quiznos", "tid": 8241, "data": {"_display": [], "slug": "/category/tags/quiznos", "content": "", "app_icon": "", "type": "2", "name": "Quiznos", "status": "1", "sponsor_category": "", "description": ""}, "type": {"name": "tags", "id": 2, "title": "Tags"}, "name": "Quiznos", "description": "", "content": 0}], "id": 82372, "thumbWithText": "http://cdn.teamcococdn.com/jokes/82372/1,1/650/jokes/may-20-2014-this-morning-a-japanese-company-unveiled-a-robot-that-can-tell-jokes-and-then-detect-if-the-joke-was-well-receiv.jpg", "slug": "jokes/may-20-2014-this-morning-a-japanese-company-unveiled-a-robot-that-can-tell-jokes-and-then-detect-if-the-joke-was-well-receiv", "body": "A Japanese company unveiled a robot that can tell jokes and then detect if the joke was well received. In a related story, I start my shift at Quiznos tomorrow.\r\n", "title": "May 20, 2014 - This morning, a Japanese company unveiled a robot that can tell jokes and then detect if the joke was well-receiv", "credit-date": "May 20, 2014", "hier1": "", "thumb": "http://cdn.teamcococdn.com/image/650x650,frame:1/20649_0574_37-537cc1f5a5abf.jpg", "tag": "main", "credit-name": "Conan O'Brien"}