{"tags": [{"tags": "", "hrefTag": "news", "status": 1, "slug": "jokes/news", "tid": 7405, "data": null, "type": {"name": "jokes", "id": 6, "title": "Jokes category"}, "name": "News", "description": "", "content": 0}, {"tags": "", "hrefTag": "fox-news", "status": 1, "slug": "category/tags/fox-news", "tid": 3355, "data": null, "type": {"name": "tags", "id": 2, "title": "Tags"}, "name": "Fox News", "description": "", "content": 3}, {"tags": "", "hrefTag": "airports", "status": 1, "slug": "category/tags/airports", "tid": 6331, "data": [], "type": {"name": "tags", "id": 2, "title": "Tags"}, "name": "Airports", "description": "", "content": 0}, {"tags": "", "hrefTag": "the-news", "status": 1, "slug": "category/tags/the-news", "tid": 7520, "data": [], "type": {"name": "tags", "id": 2, "title": "Tags"}, "name": "The News", "description": "", "content": 1}], "id": 83927, "thumbWithText": "http://cdn.teamcococdn.com/jokes/83927/1,1/650/jokes/june-26-2014-newly-revealed-video-shows-a-foxnews-anchor-at-an-airport-becoming-belligerent-and-fighting-with-cops-or-as-th.jpg", "slug": "jokes/june-26-2014-newly-revealed-video-shows-a-foxnews-anchor-at-an-airport-becoming-belligerent-and-fighting-with-cops-or-as-th", "body": "Newly revealed video shows a Fox News anchor at an airport becoming belligerent and fighting with cops. Or as that’s known at Fox News, \"an audition tape.\"", "title": "June 26, 2014 - Newly revealed video shows a FoxNews anchor at an airport becoming belligerent and fighting with cops.  Or as th", "credit-date": "June 26, 2014", "hier1": "", "thumb": "http://cdn.teamcococdn.com/image/650x650,frame:1/20649_0592_229-53ad8daea3a7a.jpg", "tag": "main", "credit-name": "Conan O'Brien"}