{"tags": [{"tags": "", "hrefTag": "news", "status": 1, "slug": "jokes/news", "tid": 7405, "data": null, "type": {"name": "jokes", "id": 6, "title": "Jokes category"}, "name": "News", "description": "", "content": 0}, {"tags": "", "hrefTag": "authors", "status": 1, "slug": "/category/tags/authors", "tid": 5663, "data": {"_display": [], "slug": "/category/tags/authors", "content": "0", "type": "2", "name": "Authors", "status": "1", "sponsor_category": "", "description": ""}, "type": {"name": "tags", "id": 2, "title": "Tags"}, "name": "Authors", "description": "", "content": 11}, {"tags": "", "hrefTag": "books", "status": 1, "slug": "category/tags/books", "tid": 6423, "data": [], "type": {"name": "tags", "id": 2, "title": "Tags"}, "name": "Books", "description": "", "content": 4}], "id": 87611, "thumbWithText": "http://cdn.teamcococdn.com/jokes/87611/1,1/650/jokes/february-3-2015-the-author-of-to-kill-a-mockingbird-is-publishing-her-second-novel-after-a-55-year-hiatus-this-one-s-entitled-mockingbird-2-mock-harder.jpg", "slug": "jokes/february-3-2015-the-author-of-to-kill-a-mockingbird-is-publishing-her-second-novel-after-a-55-year-hiatus-this-one-s-entitled-mockingbird-2-mock-harder", "body": "The author of \"To Kill A Mockingbird\" is publishing her second novel after a 55-year hiatus. This one’s entitled: \"Mockingbird 2: Mock Harder.\"", "title": "February 3, 2015 - The author of To Kill A Mockingbird is publishing her second novel after a 55-year hiatus. This one’s entitled: Mockingbird 2: Mock Harder.", "credit-date": "February 03, 2015", "hier1": "", "thumb": "http://cdn.teamcococdn.com/image/650x650,frame:1/20649-0684-46-54d174d302b68.jpg", "tag": "main", "credit-name": "Conan O'Brien"}