{"tags": [{"tags": "", "hrefTag": "politics", "status": 1, "slug": "jokes/politics", "tid": 7403, "data": null, "type": {"name": "jokes", "id": 6, "title": "Jokes category"}, "name": "Politics", "description": "", "content": 0}, {"tags": "", "hrefTag": "hillary-clinton", "status": 1, "slug": "category/tags/hillary-clinton", "tid": 1621, "data": null, "type": {"name": "tags", "id": 2, "title": "Tags"}, "name": "Hillary Clinton", "description": "", "content": 10}, {"tags": "", "hrefTag": "movies", "status": 1, "slug": "category/tags/movies", "tid": 6974, "data": [], "type": {"name": "tags", "id": 2, "title": "Tags"}, "name": "Movies", "description": "", "content": 3}, {"tags": "", "hrefTag": "women", "status": 1, "slug": "category/tags/women", "tid": 7384, "data": [], "type": {"name": "tags", "id": 2, "title": "Tags"}, "name": "Women", "description": "", "content": 2}, {"tags": "", "hrefTag": "campaigns", "status": 1, "slug": "category/tags/campaigns", "tid": 6458, "data": [], "type": {"name": "tags", "id": 2, "title": "Tags"}, "name": "Campaigns", "description": "", "content": 0}, {"tags": "", "hrefTag": "ghostbusters", "status": 1, "slug": "/category/tags/ghostbusters", "tid": 4969, "data": {"_display": [], "slug": "/category/tags/ghostbusters", "content": "0", "type": "2", "name": "Ghostbusters", "description": "", "sponsor_category": ""}, "type": {"name": "tags", "id": 2, "title": "Tags"}, "name": "Ghostbusters", "description": "", "content": 1}], "id": 88732, "thumbWithText": "http://cdn.teamcococdn.com/jokes/88732/1,1/650/jokes/april-13-2015-yesterday-hillary-clinton-made-the-big-announcement-we-all-knew-was-coming-that-s-right-she-s-going-to-join-the-all-female-cast-of-ghostbusters.jpg", "slug": "jokes/april-13-2015-yesterday-hillary-clinton-made-the-big-announcement-we-all-knew-was-coming-that-s-right-she-s-going-to-join-the-all-female-cast-of-ghostbusters", "body": "Yesterday, Hillary Clinton made the big announcement we all knew was coming. That’s right - she’s going to join the all-female cast of \"Ghostbusters.\"", "title": "April 13, 2015 - Yesterday, Hillary Clinton made the big announcement we all knew was coming. That’s right - she’s going to join the all-female cast of Ghostbusters.", "credit-date": "April 13, 2015", "hier1": "", "thumb": "http://cdn.teamcococdn.com/image/650x650,frame:1/img-3307-552c60514a5c0.jpg", "tag": "main", "credit-name": "Conan O'Brien"}