{"tags": [{"tags": "", "hrefTag": "celebs", "status": 1, "slug": "jokes/celebs", "tid": 7406, "data": null, "type": {"name": "jokes", "id": 6, "title": "Jokes category"}, "name": "Celebs", "description": "", "content": 0}, {"tags": "", "hrefTag": "donald-trump", "status": 1, "slug": "category/tags/donald-trump", "tid": 1397, "data": null, "type": {"name": "tags", "id": 2, "title": "Tags"}, "name": "Donald Trump", "description": "", "content": 44}, {"tags": "", "hrefTag": "twitter", "status": 1, "slug": "category/tags/twitter", "tid": 30, "data": null, "type": {"name": "tags", "id": 2, "title": "Tags"}, "name": "Twitter", "description": "", "content": 293}, {"tags": "", "hrefTag": "nazi", "status": 1, "slug": "/category/tags/nazi", "tid": 6180, "data": {"_display": [], "slug": "/category/tags/nazi", "content": "0", "type": "2", "name": "Nazi", "status": "1", "sponsor_category": "", "description": ""}, "type": {"name": "tags", "id": 2, "title": "Tags"}, "name": "Nazi", "description": "", "content": 5}], "id": 90365, "thumbWithText": "http://cdn.teamcococdn.com/jokes/90365/1,1/650/jokes/july-14-2015-donald-trump-s-official-twitter-account-accidentally-tweeted-a-photo-of-him-that-also-had-images-of-nazis-in-it-the-nazis-are-furious.jpg", "slug": "jokes/july-14-2015-donald-trump-s-official-twitter-account-accidentally-tweeted-a-photo-of-him-that-also-had-images-of-nazis-in-it-the-nazis-are-furious", "body": "Donald Trump’s official Twitter account accidentally tweeted a photo of him that also had images of Nazis in it. The Nazis are furious.", "title": "July 14, 2015 - Donald Trump’s official Twitter account accidentally tweeted a photo of him that also had images of Nazis in it. The Nazis are furious.", "credit-date": "July 14, 2015", "hier1": "", "thumb": "http://cdn.teamcococdn.com/image/650x650,frame:1/20649-0720-102-553e72098611b.jpg", "tag": "main", "credit-name": "Conan O'Brien"}