{"id": 94362, "title": "April 27, 2016 -  Yes I own a pair of leather pants, but they’re khaki-colored.", "tags": [{"tid": 7406, "type": {"name": "jokes", "title": "Jokes category", "id": 6}, "name": "Celebs", "description": "", "slug": "jokes/celebs", "tags": "", "content": 0, "data": null, "status": 1, "hrefTag": "celebs"}, {"tid": 24, "type": {"name": "tags", "title": "Tags", "id": 2}, "name": "CONAN", "description": "", "slug": "category/tags/conan", "tags": "", "content": 8, "data": null, "status": 1, "hrefTag": "conan"}, {"tid": 6515, "type": {"name": "tags", "title": "Tags", "id": 2}, "name": "Clothing", "description": "", "slug": "category/tags/clothing", "tags": "", "content": 1, "data": [], "status": 1, "hrefTag": "clothing"}], "body": "Yes I own a pair of leather pants, but they’re khaki-colored.", "thumb": "http://cdn.teamcococdn.com/image/650x650,frame:1/img-5774-5727942542da9.jpg", "thumbWithText": "http://cdn.teamcococdn.com/jokes/94362/1,1/650/jokes/april-27-2016-yes-i-own-a-pair-of-leather-pants-but-they-re-khaki-colored.jpg", "credit-name": "@ConanOBrien", "credit-date": "April 27, 2016", "slug": "jokes/april-27-2016-yes-i-own-a-pair-of-leather-pants-but-they-re-khaki-colored", "hier1": "", "tag": "main"}