{"id": 94674, "title": "May 24, 2016 - The security chief of the TSA has been fired. He’s been told to expect long lines at the unemployment office.", "tags": [{"tid": 7405, "type": {"name": "jokes", "title": "Jokes category", "id": 6}, "name": "News", "description": "", "slug": "jokes/news", "tags": "", "content": 0, "data": null, "status": 1, "hrefTag": "news"}, {"tid": 7326, "type": {"name": "tags", "title": "Tags", "id": 2}, "name": "TSA", "description": "", "slug": "category/tags/tsa", "tags": "", "content": 11, "data": [], "status": 1, "hrefTag": "tsa"}, {"tid": 6608, "type": {"name": "tags", "title": "Tags", "id": 2}, "name": "Employment", "description": "", "slug": "category/tags/employment", "tags": "", "content": 0, "data": [], "status": 1, "hrefTag": "employment"}], "body": "The security chief of the TSA has been fired. He’s been told to expect long lines at the unemployment office.", "thumb": "http://cdn.teamcococdn.com/image/650x650,frame:1/img-3196-574502871b356.jpg", "thumbWithText": "http://cdn.teamcococdn.com/jokes/94674/1,1/650/jokes/may-24-2016-the-security-chief-of-the-tsa-has-been-fired-he-s-been-told-to-expect-long-lines-at-the-unemployment-office.jpg", "credit-name": "Conan O'Brien", "credit-date": "May 24, 2016", "slug": "jokes/may-24-2016-the-security-chief-of-the-tsa-has-been-fired-he-s-been-told-to-expect-long-lines-at-the-unemployment-office", "hier1": "", "tag": "main"}