{"id": 94867, "title": "June 7, 2016 - I wish I had a 3D print of my regrets.", "tags": [{"tid": 7406, "type": {"name": "jokes", "title": "Jokes category", "id": 6}, "name": "Celebs", "description": "", "slug": "jokes/celebs", "tags": "", "content": 0, "data": null, "status": 1, "hrefTag": "celebs"}, {"tid": 6307, "type": {"name": "tags", "title": "Tags", "id": 2}, "name": "3D Printing", "description": "", "slug": "category/tags/3d-printing", "tags": "", "content": 0, "data": [], "status": 1, "hrefTag": "3d-printing"}, {"tid": 24, "type": {"name": "tags", "title": "Tags", "id": 2}, "name": "CONAN", "description": "", "slug": "category/tags/conan", "tags": "", "content": 8, "data": null, "status": 1, "hrefTag": "conan"}], "body": "I wish I had a 3D print of my regrets.", "thumb": "http://cdn.teamcococdn.com/image/650x650,frame:1/img-2948-575ef100b7884.jpg", "thumbWithText": "http://cdn.teamcococdn.com/jokes/94867/1,1/650/jokes/june-7-2016-i-wish-i-had-a-3d-print-of-my-regrets.jpg", "credit-name": "@ConanOBrien", "credit-date": "June 07, 2016", "slug": "jokes/june-7-2016-i-wish-i-had-a-3d-print-of-my-regrets", "hier1": "", "tag": "main"}