{"id": 95229, "title": "June 30, 2016 - To my fellow hikers: that noise I made when the butterfly came toward my face was a terrified shriek of delight. 956 retweets 5,401 likes", "tags": [{"tid": 7406, "type": {"name": "jokes", "title": "Jokes category", "id": 6}, "name": "Celebs", "description": "", "slug": "jokes/celebs", "tags": "", "content": 0, "data": null, "status": 1, "hrefTag": "celebs"}, {"tid": 6640, "type": {"name": "tags", "title": "Tags", "id": 2}, "name": "Fitness", "description": "", "slug": "category/tags/fitness", "tags": "", "content": 1, "data": [], "status": 1, "hrefTag": "fitness"}, {"tid": 6619, "type": {"name": "tags", "title": "Tags", "id": 2}, "name": "Exercise", "description": "", "slug": "category/tags/exercise", "tags": "", "content": 10, "data": [], "status": 1, "hrefTag": "exercise"}], "body": "To my fellow hikers: that noise I made when the butterfly came toward my face was a terrified shriek of delight.", "thumb": "http://cdn.teamcococdn.com/image/650x650,frame:1/img-7153-577d4ce6d3865.jpg", "thumbWithText": "http://cdn.teamcococdn.com/jokes/95229/1,1/650/jokes/june-30-2016-to-my-fellow-hikers-that-noise-i-made-when-the-butterfly-came-toward-my-face-was-a-terrified-shriek-of-delight-956-retweets-5-401-likes.jpg", "credit-name": "@ConanOBrien", "credit-date": "July 06, 2016", "slug": "jokes/june-30-2016-to-my-fellow-hikers-that-noise-i-made-when-the-butterfly-came-toward-my-face-was-a-terrified-shriek-of-delight-956-retweets-5-401-likes", "hier1": "", "tag": "main"}