{"id": 98142, "title": "December 20, 2016 - A new study has proven that animals do indeed have personalities. As expected, the study also confirmed that all cats are dicks.", "tags": [{"tid": 7405, "type": {"name": "jokes", "title": "Jokes category", "id": 6}, "name": "News", "description": "", "slug": "jokes/news", "tags": "", "content": 0, "data": null, "status": 1, "hrefTag": "news"}, {"tid": 163, "type": {"name": "tags", "title": "Tags", "id": 2}, "name": "Cats", "description": "", "slug": "category/tags/cats", "tags": "", "content": 22, "data": null, "status": 1, "hrefTag": "cats"}, {"tid": 6348, "type": {"name": "tags", "title": "Tags", "id": 2}, "name": "Animals", "description": "", "slug": "category/tags/animals", "tags": "", "content": 17, "data": [], "status": 1, "hrefTag": "animals"}, {"tid": 7228, "type": {"name": "tags", "title": "Tags", "id": 2}, "name": "Studies", "description": "", "slug": "category/tags/studies", "tags": "", "content": 0, "data": [], "status": 1, "hrefTag": "studies"}], "body": "A new study has proven that animals do indeed have personalities. As expected, the study also confirmed that all cats are dicks.", "thumb": "http://cdn.teamcococdn.com/image/650x650,frame:1/206490969290-5859e593c638d.jpg", "thumbWithText": "http://cdn.teamcococdn.com/jokes/98142/1,1/650/jokes/december-20-2016-a-new-study-has-proven-that-animals-do-indeed-have-personalities-as-expected-the-study-also-confirmed-that-all-cats-are-dicks.jpg", "credit-name": "Conan O'Brien", "credit-date": "December 20, 2016", "slug": "jokes/december-20-2016-a-new-study-has-proven-that-animals-do-indeed-have-personalities-as-expected-the-study-also-confirmed-that-all-cats-are-dicks", "hier1": "", "tag": "main"}