{"id": 99648, "title": "April 19, 2017 - A recent security purge by Facebook has unintentionally gotten rid of millions of \"likes.” Just think... all those wasted hours, wasted.", "tags": [{"tid": 7404, "type": {"name": "jokes", "title": "Jokes category", "id": 6}, "name": "Tech", "description": "", "slug": "jokes/tech", "tags": "", "content": 0, "data": null, "status": 1, "hrefTag": "tech"}, {"tid": 149, "type": {"name": "tags", "title": "Tags", "id": 2}, "name": "Facebook", "description": "", "slug": "category/tags/facebook", "tags": "", "content": 44, "data": null, "status": 1, "hrefTag": "facebook"}], "body": "A recent security purge by Facebook has unintentionally gotten rid of millions of \"likes.” Just think... all those wasted hours, wasted.", "thumb": "http://cdn.teamcococdn.com/image/650x650,frame:1/3p9a8761-58f803d02b2c1.jpg", "thumbWithText": "http://cdn.teamcococdn.com/jokes/99648/1,1/650/jokes/april-19-2017-a-recent-security-purge-by-facebook-has-unintentionally-gotten-rid-of-millions-of-likes-just-think-all-those-wasted-hours-wasted.jpg", "credit-name": "Conan O'Brien", "credit-date": "April 19, 2017", "slug": "jokes/april-19-2017-a-recent-security-purge-by-facebook-has-unintentionally-gotten-rid-of-millions-of-likes-just-think-all-those-wasted-hours-wasted", "hier1": "", "tag": "main"}